repaint/__init__.py
repaint/cli.py
repaint/core.py
repaint/events.py
repaint/js/browser.js
repaint/js/browser.js.map
repaint/server.py
repaint-0.1.0.dist-info/entry_points.txt
repaint-0.1.0.dist-info/LICENSE
repaint-0.1.0.dist-info/WHEEL
repaint-0.1.0.dist-info/METADATA
repaint-0.1.0.dist-info/RECORD
